aza_api/__init__.py
aza_api/aza_api.py
aza_api/aza_api2.py
aza_api/fetch_portfolio.py
aza_api/html_to_df.py
aza_api/login_aza.py
aza_api/map_aza_stock_to_url.py
aza_api-0.0.13.dist-info/LICENSE
aza_api-0.0.13.dist-info/METADATA
aza_api-0.0.13.dist-info/WHEEL
aza_api-0.0.13.dist-info/top_level.txt
aza_api-0.0.13.dist-info/RECORD
