Metadata-Version: 2.1
Name: aza-api
Version: 0.0.13
Summary: Package to fetch data from Avanza
Home-page: https://github.com/olundberg/aza_api
Author: Oscar Lundberg
Author-email: lundberg.oscar@gmail.com
License: UNKNOWN
Download-URL: https://github.com/olundberg/aza_api/archive/refs/tags/v_0.0.13.tar.gz
Platform: UNKNOWN
Classifier: Programming Language :: Python :: 3
Classifier: License :: OSI Approved :: MIT License
Classifier: Operating System :: OS Independent
Requires-Python: >=3.9
License-File: LICENSE
Requires-Dist: webdriver-manager
Requires-Dist: selenium (>=3.141.0)
